rain/__init__.py
rain/capnp/client.capnp
rain/capnp/common.capnp
rain/capnp/governor.capnp
rain/capnp/monitor.capnp
rain/capnp/server.capnp
rain/client/__init__.py
rain/client/client.py
rain/client/data.py
rain/client/graph.py
rain/client/input.py
rain/client/output.py
rain/client/program.py
rain/client/pycode.py
rain/client/rpc.py
rain/client/session.py
rain/client/task.py
rain/client/tasks.py
rain/common/__init__.py
rain/common/attributes.py
rain/common/comm.py
rain/common/content_type.py
rain/common/data_instance.py
rain/common/data_type.py
rain/common/errors.py
rain/common/fs.py
rain/common/ids.py
rain/common/labeled_list.py
rain/common/utils.py
rain/executor/__init__.py
rain/executor/__main__.py
rain/executor/context.py
rain/executor/executor.py
rain_python-0.4.0.dist-info/METADATA
rain_python-0.4.0.dist-info/RECORD
rain_python-0.4.0.dist-info/WHEEL
rain_python-0.4.0.dist-info/top_level.txt
