Metadata-Version: 2.1
Name: rain-python
Version: 0.4.0
Summary: Distributed Computational Framework
Home-page: https://github.com/substantic/rain
Author: Stanislav Bohm, Vojtech Cima, Tomas Gavenciak
Author-email: rain@substantic.net
License: MIT
Platform: UNKNOWN
Requires-Dist: cbor
Requires-Dist: cloudpickle
Requires-Dist: pyarrow
Requires-Dist: pycapnp
